graphery/__init__.py
graphery/graph.py
graphery/graph_generator.py
graphery-0.1.1.dist-info/LICENSE
graphery-0.1.1.dist-info/METADATA
graphery-0.1.1.dist-info/WHEEL
graphery-0.1.1.dist-info/top_level.txt
graphery-0.1.1.dist-info/RECORD
