Metadata-Version: 2.1
Name: graphery
Version: 0.1.1
Summary: Digital terrain map manipulation high level functions
Home-page: https://gitlab.com/frontierdevelopmentlab/space-resources/graphery
Author: Red Boumghar
License: BSD
Keywords: GDAL,graph,navigation,cost,traverse,traversability,robots,astar,ai
Platform: UNKNOWN
Classifier: Development Status :: 3 - Alpha
Classifier: Intended Audience :: Developers
Classifier: Programming Language :: Python :: 3
Classifier: License :: OSI Approved :: BSD License
Requires-Python: >=3
Requires-Dist: mapstery
Requires-Dist: geojson
Requires-Dist: networkx
Requires-Dist: numpy
Provides-Extra: test
Requires-Dist: pytest ; extra == 'test'
